FSMD/__init__.py
FSMD/install.py
FSMD/main.py
FSMD-1.1.0.dist-info/LICENSE.txt
FSMD-1.1.0.dist-info/METADATA
FSMD-1.1.0.dist-info/WHEEL
FSMD-1.1.0.dist-info/entry_points.txt
FSMD-1.1.0.dist-info/top_level.txt
FSMD-1.1.0.dist-info/RECORD
