Metadata-Version: 2.1
Name: FSMD
Version: 1.1.0
Summary: A CLI tool for creating an FSM diagram.
Home-page: https://github.com/jaxcksn/FSMD
Author: Jaxcksn
Author-email: admin@texansim.com
License: GPLv3
Project-URL: Bug Tracker, https://github.com/jaxcksn/FSMD/issues
Classifier: Programming Language :: Python :: 3
Classifier: License :: OSI Approved :: GNU General Public License v3 (GPLv3)
Classifier: Operating System :: OS Independent
Classifier: Programming Language :: Python :: 3.7
Classifier: Programming Language :: Python :: 3.8
Classifier: Programming Language :: Python :: 3.9
Classifier: Programming Language :: Python :: 3.10
Classifier: Programming Language :: Python :: 3.11
Requires-Python: >3.7
License-File: LICENSE.txt
Requires-Dist: graphviz ==0.20.1
Requires-Dist: PyYAML ==6.0.1
Requires-Dist: Requests ==2.31.0
Requires-Dist: rich ==13.5.3
Requires-Dist: typer ==0.9.0
Requires-Dist: typing-extensions ==4.8.0
Requires-Dist: schema ==0.7.5
